the_keyspy/__init__.py
the_keyspy/api.py
the_keyspy/dataclasses.py
the_keyspy/errors.py
the_keyspy/devices/__init__.py
the_keyspy/devices/base.py
the_keyspy/devices/gateway.py
the_keyspy/devices/lock.py
the_keyspy-0.0.25.dist-info/METADATA
the_keyspy-0.0.25.dist-info/WHEEL
the_keyspy-0.0.25.dist-info/top_level.txt
the_keyspy-0.0.25.dist-info/RECORD
