Metadata-Version: 2.4
Name: the_keyspy
Version: 0.0.25
Summary: The Keys Api
Author-email: Kevin Bonnoron <kevin.bonnoron@gmail.com>
License: MIT
Keywords: the-keys
